{
  "code": 200,
  "msg": "OK",
  "data": {
    "page": 1,
    "size": 10,
    "total": 2918,
    "rows": [
      {
        "application_id": 7710,
        "season_name": "S3",
        "entity_name": "投研公会",
        "entity_id": "6",
        "entity_type": "guild",
        "asset_name": "SCR",
        "amount": "200",
        "budget_source": "投研公会",
        "status": "completed",
        "detailed_type": "补登S2月积分",
        "comment": "",
        "app_bundle_comment": "test s5",
        "target_user_wallet": "0xb789a1297b1f5d46435d1679e18696438a795b04",
        "target_user_avatar": "",
        "applicant_wallet": "",
        "applicant_avatar": "",
        "apply_ts": 0,
        "reviewer_wallet": "",
        "reviewer_avatar": "",
        "review_ts": 0,
        "processor_wallet": "",
        "processor_avatar": "",
        "process_ts": 0,
        "completer_wallet": "",
        "completer_avatar": "",
        "complete_ts": 0,
        "transaction_ids": "",
        "create_ts": 0,
        "update_ts": 0
      },
      {
        "application_id": 7711,
        "season_name": "S3",
        "entity_name": "投研公会",
        "entity_id": "6",
        "entity_type": "guild",
        "asset_name": "SCR",
        "amount": "200",
        "budget_source": "投研公会",
        "status": "completed",
        "detailed_type": "补登S2月积分",
        "comment": "",
        "app_bundle_comment": "test s5",
        "target_user_wallet": "0xad483c143903a8a35ce15133e7dd99d4d6af732c",
        "target_user_avatar": "",
        "applicant_wallet": "",
        "applicant_avatar": "",
        "apply_ts": 0,
        "reviewer_wallet": "",
        "reviewer_avatar": "",
        "review_ts": 0,
        "processor_wallet": "",
        "processor_avatar": "",
        "process_ts": 0,
        "completer_wallet": "",
        "completer_avatar": "",
        "complete_ts": 0,
        "transaction_ids": "",
        "create_ts": 0,
        "update_ts": 0
      },
      {
        "application_id": 7712,
        "season_name": "S3",
        "entity_name": "投研公会",
        "entity_id": "6",
        "entity_type": "guild",
        "asset_name": "SCR",
        "amount": "200",
        "budget_source": "投研公会",
        "status": "completed",
        "detailed_type": "补登S2月积分",
        "comment": "",
        "app_bundle_comment": "test s5",
        "target_user_wallet": "0xda131dc2c646d524f42acb8dc69fa38a9c6d87f9",
        "target_user_avatar": "",
        "applicant_wallet": "",
        "applicant_avatar": "",
        "apply_ts": 0,
        "reviewer_wallet": "",
        "reviewer_avatar": "",
        "review_ts": 0,
        "processor_wallet": "",
        "processor_avatar": "",
        "process_ts": 0,
        "completer_wallet": "",
        "completer_avatar": "",
        "complete_ts": 0,
        "transaction_ids": "",
        "create_ts": 0,
        "update_ts": 0
      },
      {
        "application_id": 7713,
        "season_name": "S3",
        "entity_name": "投研公会",
        "entity_id": "6",
        "entity_type": "guild",
        "asset_name": "SCR",
        "amount": "200",
        "budget_source": "投研公会",
        "status": "completed",
        "detailed_type": "补登S2月积分",
        "comment": "",
        "app_bundle_comment": "test s5",
        "target_user_wallet": "0x6cb1429535e053abd203e64f8020564c649b14a6",
        "target_user_avatar": "",
        "applicant_wallet": "",
        "applicant_avatar": "",
        "apply_ts": 0,
        "reviewer_wallet": "",
        "reviewer_avatar": "",
        "review_ts": 0,
        "processor_wallet": "",
        "processor_avatar": "",
        "process_ts": 0,
        "completer_wallet": "",
        "completer_avatar": "",
        "complete_ts": 0,
        "transaction_ids": "",
        "create_ts": 0,
        "update_ts": 0
      },
      {
        "application_id": 7714,
        "season_name": "S3",
        "entity_name": "投研公会",
        "entity_id": "6",
        "entity_type": "guild",
        "asset_name": "SCR",
        "amount": "200",
        "budget_source": "投研公会",
        "status": "completed",
        "detailed_type": "补登S2月积分",
        "comment": "",
        "app_bundle_comment": "test s5",
        "target_user_wallet": "0x1e920de22ab994204a7f357f1ce4046544984de8",
        "target_user_avatar": "",
        "applicant_wallet": "",
        "applicant_avatar": "",
        "apply_ts": 0,
        "reviewer_wallet": "",
        "reviewer_avatar": "",
        "review_ts": 0,
        "processor_wallet": "",
        "processor_avatar": "",
        "process_ts": 0,
        "completer_wallet": "",
        "completer_avatar": "",
        "complete_ts": 0,
        "transaction_ids": "",
        "create_ts": 0,
        "update_ts": 0
      },
      {
        "application_id": 7715,
        "season_name": "S3",
        "entity_name": "投研公会",
        "entity_id": "6",
        "entity_type": "guild",
        "asset_name": "SCR",
        "amount": "200",
        "budget_source": "投研公会",
        "status": "completed",
        "detailed_type": "补登S2月积分",
        "comment": "",
        "app_bundle_comment": "test s5",
        "target_user_wallet": "0x89c60c01f2e1d1b233253596bf1c2386bdfeb898",
        "target_user_avatar": "",
        "applicant_wallet": "",
        "applicant_avatar": "",
        "apply_ts": 0,
        "reviewer_wallet": "",
        "reviewer_avatar": "",
        "review_ts": 0,
        "processor_wallet": "",
        "processor_avatar": "",
        "process_ts": 0,
        "completer_wallet": "",
        "completer_avatar": "",
        "complete_ts": 0,
        "transaction_ids": "",
        "create_ts": 0,
        "update_ts": 0
      },
      {
        "application_id": 7716,
        "season_name": "S3",
        "entity_name": "投研公会",
        "entity_id": "6",
        "entity_type": "guild",
        "asset_name": "SCR",
        "amount": "200",
        "budget_source": "投研公会",
        "status": "completed",
        "detailed_type": "补登S2月积分",
        "comment": "",
        "app_bundle_comment": "test s5",
        "target_user_wallet": "0x608a9358354a93581e686ac7ffde9d5fadbcb7e0",
        "target_user_avatar": "",
        "applicant_wallet": "",
        "applicant_avatar": "",
        "apply_ts": 0,
        "reviewer_wallet": "",
        "reviewer_avatar": "",
        "review_ts": 0,
        "processor_wallet": "",
        "processor_avatar": "",
        "process_ts": 0,
        "completer_wallet": "",
        "completer_avatar": "",
        "complete_ts": 0,
        "transaction_ids": "",
        "create_ts": 0,
        "update_ts": 0
      },
      {
        "application_id": 7717,
        "season_name": "S3",
        "entity_name": "投研公会",
        "entity_id": "6",
        "entity_type": "guild",
        "asset_name": "SCR",
        "amount": "200",
        "budget_source": "投研公会",
        "status": "completed",
        "detailed_type": "补登S2月积分",
        "comment": "",
        "app_bundle_comment": "test s5",
        "target_user_wallet": "0x016df27c5a9e479ab01e3053cd5a1967f96ecd6e",
        "target_user_avatar": "",
        "applicant_wallet": "",
        "applicant_avatar": "",
        "apply_ts": 0,
        "reviewer_wallet": "",
        "reviewer_avatar": "",
        "review_ts": 0,
        "processor_wallet": "",
        "processor_avatar": "",
        "process_ts": 0,
        "completer_wallet": "",
        "completer_avatar": "",
        "complete_ts": 0,
        "transaction_ids": "",
        "create_ts": 0,
        "update_ts": 0
      },
      {
        "application_id": 7718,
        "season_name": "S3",
        "entity_name": "投研公会",
        "entity_id": "6",
        "entity_type": "guild",
        "asset_name": "SCR",
        "amount": "200",
        "budget_source": "投研公会",
        "status": "completed",
        "detailed_type": "补登S2月积分",
        "comment": "",
        "app_bundle_comment": "test s5",
        "target_user_wallet": "0xddf29c0e97601d8ab661c4b3c3a8ac7d9bd5cb77",
        "target_user_avatar": "",
        "applicant_wallet": "",
        "applicant_avatar": "",
        "apply_ts": 0,
        "reviewer_wallet": "",
        "reviewer_avatar": "",
        "review_ts": 0,
        "processor_wallet": "",
        "processor_avatar": "",
        "process_ts": 0,
        "completer_wallet": "",
        "completer_avatar": "",
        "complete_ts": 0,
        "transaction_ids": "",
        "create_ts": 0,
        "update_ts": 0
      },
      {
        "application_id": 7719,
        "season_name": "S3",
        "entity_name": "投研公会",
        "entity_id": "6",
        "entity_type": "guild",
        "asset_name": "SCR",
        "amount": "200",
        "budget_source": "投研公会",
        "status": "completed",
        "detailed_type": "补登S2月积分",
        "comment": "",
        "app_bundle_comment": "test s5",
        "target_user_wallet": "0x7ffca0796a835d2de97f5f038d8c94de0249624d",
        "target_user_avatar": "",
        "applicant_wallet": "",
        "applicant_avatar": "",
        "apply_ts": 0,
        "reviewer_wallet": "",
        "reviewer_avatar": "",
        "review_ts": 0,
        "processor_wallet": "",
        "processor_avatar": "",
        "process_ts": 0,
        "completer_wallet": "",
        "completer_avatar": "",
        "complete_ts": 0,
        "transaction_ids": "",
        "create_ts": 0,
        "update_ts": 0
      }
    ]
  }
}
